LICENSE.txt
README.md
setup.py
torch_hyperbolic/__init__.py
torch_hyperbolic/manifolds.py
torch_hyperbolic/optim.py
torch_hyperbolic/utils.py
torch_hyperbolic.egg-info/PKG-INFO
torch_hyperbolic.egg-info/SOURCES.txt
torch_hyperbolic.egg-info/dependency_links.txt
torch_hyperbolic.egg-info/requires.txt
torch_hyperbolic.egg-info/top_level.txt
torch_hyperbolic/models/__init__.py
torch_hyperbolic/models/hgnn.py
torch_hyperbolic/models/hgnn_film.py
torch_hyperbolic/nn/__init__.py
torch_hyperbolic/nn/hact.py
torch_hyperbolic/nn/hdecoder.py
torch_hyperbolic/nn/hencoder.py
torch_hyperbolic/nn/hfilm.py
torch_hyperbolic/nn/hgat.py
torch_hyperbolic/nn/hgcn.py
torch_hyperbolic/nn/hlinear.py