Metadata-Version: 2.1
Name: torch-hyperbolic
Version: 0.0.3
Summary: Hyperbolic NNs and GNNs in torch
Author: Florin Ratajczak
License-File: LICENSE.txt
